boxofficepy/BoxOffice.py
boxofficepy/__init__.py
BoxOfficepy-0.0.2.dist-info/METADATA
BoxOfficepy-0.0.2.dist-info/WHEEL
BoxOfficepy-0.0.2.dist-info/top_level.txt
BoxOfficepy-0.0.2.dist-info/RECORD
