Metadata-Version: 2.1
Name: BoxOfficepy
Version: 0.0.2
Summary: A Package to get Box Office Revenue
Author: rahul192 (Rahul Raj Singh)
Author-email: <rahul.raj.singh220899@gmail.com>
Keywords: python,revenue,box office
Classifier: Development Status :: 1 - Planning
Classifier: Intended Audience :: Developers
Classifier: Programming Language :: Python :: 3
Classifier: Operating System :: Unix
Classifier: Operating System :: MacOS :: MacOS X
Classifier: Operating System :: Microsoft :: Windows
Requires-Dist: datetime
Requires-Dist: requests
Requires-Dist: pandas
Requires-Dist: requests-html
